spatialrna/__init__.py
spatialrna/run_kmeans.py
spatialrna/spatialrna.py
spatialrna/spatialrna_ondisk.py
spatialrna/train_val.py
spatialrna/viz.py
spatialrna-0.2.0.dist-info/licenses/LICENSE.txt
spatialrna-0.2.0.dist-info/METADATA
spatialrna-0.2.0.dist-info/WHEEL
spatialrna-0.2.0.dist-info/top_level.txt
spatialrna-0.2.0.dist-info/RECORD
