Metadata-Version: 2.4
Name: spatialrna
Version: 0.2.0
Summary: A package for spatial RNA graph data processing and analysis.
Author-email: Ruqian Lyu <rlyu@svi.edu.au>
License: MIT
Project-URL: repository, https://github.com/ruqianl/spatialrna.git
Classifier: License :: OSI Approved :: MIT License
Classifier: Programming Language :: Python :: 3.10
Classifier: Operating System :: OS Independent
Requires-Python: >=3.10
License-File: LICENSE.txt
Requires-Dist: torch
Requires-Dist: torch_geometric
Requires-Dist: pandas
Requires-Dist: numpy
Provides-Extra: dev
Requires-Dist: pytest>=6.0; extra == "dev"
Requires-Dist: twine>=4.0.2; extra == "dev"
Requires-Dist: build; extra == "dev"
Dynamic: license-file
